descripstats/__init__.py
descripstats/stats.py
descripstats-0.0.2.dist-info/LICENSE
descripstats-0.0.2.dist-info/METADATA
descripstats-0.0.2.dist-info/WHEEL
descripstats-0.0.2.dist-info/top_level.txt
descripstats-0.0.2.dist-info/RECORD
