Metadata-Version: 2.1
Name: descripstats
Version: 0.0.2
Summary: A descriptive statistics package
Home-page: https://github.com/shoukewei/descripstats
Author: Shouke Wei
Author-email: shouke.wei@gmail.com
License: MIT License
Keywords: python,descriptive statistics,more measures,pandas describe,pandas dataframe
Classifier: Development Status :: 1 - Planning
Classifier: Intended Audience :: Science/Research
Classifier: Programming Language :: Python :: 3
Classifier: Operating System :: Unix
Classifier: Operating System :: MacOS :: MacOS X
Classifier: Operating System :: Microsoft :: Windows
License-File: LICENSE
Requires-Dist: pandas
